weather_fetcher/__init__.py
weather_fetcher/api.py
weather_fetcher/core.py
weather_fetcher/server.py
weather_fetcher/utils.py
weather_fetcher-0.1.2.dist-info/LICENSE
weather_fetcher-0.1.2.dist-info/METADATA
weather_fetcher-0.1.2.dist-info/WHEEL
weather_fetcher-0.1.2.dist-info/top_level.txt
weather_fetcher-0.1.2.dist-info/RECORD
