Metadata-Version: 2.1
Name: weather-fetcher
Version: 0.1.2
Summary: A Python package to fetch weather data
Home-page: https://github.com/testinapps/python-weather-app
Author: Your Name
Author-email: your_email@example.com
Project-URL: Bug Tracker, https://github.com/testinapps/python-weather-app/issues
Project-URL: Documentation, https://github.com/testinapps/python-weather-app/wiki
Project-URL: Source Code, https://github.com/testinapps/python-weather-app
Classifier: Programming Language :: Python :: 3
Classifier: License :: OSI Approved :: MIT License
Classifier: Operating System :: OS Independent
Requires-Python: >=3.6
License-File: LICENSE
Requires-Dist: certifi==2024.8.30
Requires-Dist: charset-normalizer==3.4.0
Requires-Dist: idna==3.10
Requires-Dist: requests==2.32.3
Requires-Dist: urllib3==2.2.3
Provides-Extra: dev
Requires-Dist: flake8==6.1.0; extra == "dev"
Requires-Dist: black==23.9.1; extra == "dev"
Requires-Dist: pytest==8.3.4; extra == "dev"
Requires-Dist: build==1.2.2.post1; extra == "dev"
Requires-Dist: twine==6.0.1; extra == "dev"
